djgo/__init__.py
djgo/admin.py
djgo/djgo.py
djgo-0.0.2.dist-info/LICENSE
djgo-0.0.2.dist-info/WHEEL
djgo-0.0.2.dist-info/METADATA
djgo-0.0.2.dist-info/RECORD
