Metadata-Version: 2.1
Name: djgo
Version: 0.0.2
Summary: A pack of shortcuts for Django.
Home-page: https://github.com/Ceterai/djgo
License: MIT
Author: Ceterai
Author-email: ceterai@protonmail.com
Requires-Python: >=3.8,<4.0
Classifier: License :: OSI Approved :: MIT License
Classifier: Operating System :: OS Independent
Classifier: Programming Language :: Python :: 3
Classifier: Programming Language :: Python :: 3.8
Requires-Dist: django (>=3.0.0,<4.0.0)
Project-URL: Repository, https://github.com/Ceterai/djgo
